xacc/xaccvqe.py
xacc/_pyxaccvqe.so
xacc/xaccvqe-config.cmake
xacc/py-plugins/vqe_energy.py
xacc/py-plugins/hamiltonian_generator.py
xacc/py-plugins/vqe_param_sweep.py
xacc/py-plugins/vqe.py
xacc/py-plugins/wrappedVQE.py
xacc/py-plugins/wrappedVQEEnergy.py
xacc/py-plugins/vqe_base.py
xacc/py-plugins/ansatzgenerator.py
xacc/plugins/libxacc-vqe-decorators.so
xacc/plugins/libxacc-vqe-tasks.so
xacc/plugins/libxacc-vqe-irtransformations.so
xacc/plugins/libxacc-vqe-fermion-compiler.so
xacc/plugins/libxacc-vqe-ir.so
xacc/plugins/libxacc-vqe-no-mpi.so
xacc/include/vqe/FermionKernel.hpp
xacc/include/vqe/FermionInstruction.hpp
xacc/include/vqe/EfficientJW.hpp
xacc/include/vqe/HWE.hpp
xacc/include/vqe/FermionCompiler.hpp
xacc/include/vqe/UCCSD.hpp
xacc/include/vqe/ProfileHamiltonianTask.hpp
xacc/include/vqe/BravyiKitaevIRTransformation.hpp
xacc/include/vqe/FermionToSpinTransformation.hpp
xacc/include/vqe/LongRangeJW.hpp
xacc/include/vqe/JordanWignerIRTransformation.hpp
xacc/include/vqe/PsoVQEBackend.hpp
xacc/include/vqe/VQERestartDecorator.hpp
xacc/include/vqe/MPIProvider.hpp
xacc/include/vqe/SlepcDiagonalizeBackend.hpp
xacc/include/vqe/DiagonalizeTask.hpp
xacc/include/vqe/CommutingSetGenerator.hpp
xacc/include/vqe/TaoVQEBackend.hpp
xacc/include/vqe/QubitTapering.hpp
xacc/include/vqe/VQEProgram.hpp
xacc/include/vqe/ComputeEnergyVQETask.hpp
xacc/include/vqe/FermionIR.hpp
xacc/include/vqe/Program.hpp
xacc/include/vqe/PurificationDecorator.hpp
xacc/include/vqe/GenerateOpenFermionEigenspectrumScript.hpp
xacc/include/vqe/Fenwick.hpp
xacc/include/vqe/operators.hpp
xacc/include/vqe/SymVerificationDecorator.hpp
xacc/include/vqe/RDMGenerator.hpp
xacc/include/vqe/VQEParameterGenerator.hpp
xacc/include/vqe/VQETask.hpp
xacc/include/vqe/VQEMinimizeTask.hpp
xacc/include/vqe/RDMPurificationDecorator.hpp
xacc/include/cppoptlib/meta.h
xacc/include/cppoptlib/boundedproblem.h
xacc/include/cppoptlib/problem.h
xacc/include/cppoptlib/BUILD
xacc_vqe-0.1.14.dist-info/top_level.txt
xacc_vqe-0.1.14.dist-info/DESCRIPTION.rst
xacc_vqe-0.1.14.dist-info/METADATA
xacc_vqe-0.1.14.dist-info/WHEEL
xacc_vqe-0.1.14.dist-info/RECORD
xacc_vqe-0.1.14.dist-info/metadata.json
