Metadata-Version: 2.0
Name: xacc-vqe
Version: 0.1.14
Summary: Hardware-agnostic quantum programming framework
Home-page: UNKNOWN
Author: Alex McCaskey
Author-email: xacc-dev@eclipse.org
License: UNKNOWN
Platform: UNKNOWN
Requires-Dist: xacc (>=0.1.15)
